{
  "extensions": {
    ".java": {
      "extension":".java",
      "beginSingleLineComment":"//",
      "endSingleLineComment":"\n",
      "beginMultiLineComment":"\/\\*",
      "endMultiLineComment":"\\*\/",
      "name": "Java"
    },
    ".py": {
      "beginSingleLineComment":"#",
      "endSingleLineComment":"\n",
      "beginMultiLineComment":"\"\"\"",
      "endMultiLineComment":"\"\"\"",
      "name": "Python",
      "extension":".py"
    },
    ".js": {
      "beginSingleLineComment":"//",
      "endSingleLineComment":"\n",
      "beginMultiLineComment":"\/\\*",
      "endMultiLineComment":"\\*\/",
      "name": "JavaScript",
      "extension":".js"
    },
    ".ts": {
      "beginSingleLineComment":"//",
      "endSingleLineComment":"\n",
      "beginMultiLineComment":"\/\\*",
      "endMultiLineComment":"\\*\/",
      "name": "TypeScript",
      "extension":".ts"
    },
    ".rb": {
      "beginSingleLineComment":"#",
      "endSingleLineComment":"\n",
      "beginMultiLineComment":"=begin",
      "endMultiLineComment":"=end",
      "name": "Ruby",
      "extension":".rb"
    },
    ".php": {
      "beginSingleLineComment":"//",
      "endSingleLineComment":"\n",
      "beginMultiLineComment":"\/\\*",
      "endMultiLineComment":"\\*\/",
      "name": "PHP",
      "extension":".php"
    },
    ".cpp": {
      "beginSingleLineComment":"//",
      "endSingleLineComment":"\n",
      "beginMultiLineComment":"\/\\*",
      "endMultiLineComment":"\\*\/",
      "name": "C++",
      "extension":".cpp"
    },
    ".cs": {
      "beginSingleLineComment":"//",
      "endSingleLineComment":"\n",
      "beginMultiLineComment":"\/\\*",
      "endMultiLineComment":"\\*\/",
      "name": "C#",
      "extension":".cs"
    },
    ".c": {
      "beginSingleLineComment":"//",
      "endSingleLineComment":"\n",
      "beginMultiLineComment":"\/\\*",
      "endMultiLineComment":"\\*\/",
      "name": "C",
      "extension":".c"
    },
    ".go": {
      "beginSingleLineComment":"//",
      "endSingleLineComment":"\n",
      "beginMultiLineComment":"\/\\*",
      "endMultiLineComment":"\\*\/",
      "name": "Go",
      "extension":".go"
    },
    ".swift": {
      "beginSingleLineComment":"//",
      "endSingleLineComment":"\n",
      "beginMultiLineComment":"\/\\*",
      "endMultiLineComment":"\\*\/",
      "name": "Swift",
      "extension":".swift"
    },
    ".kt": {
      "beginSingleLineComment":"//",
      "endSingleLineComment":"\n",
      "beginMultiLineComment":"\/\\*",
      "endMultiLineComment":"\\*\/",
      "name": "Kotlin",
      "extension":".kt"
    },
    ".rs": {
      "beginSingleLineComment":"//",
      "endSingleLineComment":"\n",
      "beginMultiLineComment":"\/\\*",
      "endMultiLineComment":"\\*\/",
      "name": "Rust",
      "extension":".rs"
    },
    ".scala": {
      "beginSingleLineComment":"//",
      "endSingleLineComment":"\n",
      "beginMultiLineComment":"\/\\*",
      "endMultiLineComment":"\\*\/",
      "name": "Scala",
      "extension":".scala"
    },
    ".html": {
      "beginSingleLineComment":"//",
      "endSingleLineComment":"\n",
      "beginMultiLineComment":"<!--",
      "endMultiLineComment":"-->",
      "name": "HTML",
      "extension":".html"
    }
  }
}
